{"type":"FeatureCollection","crs":{"type":"name","properties":{"name":"EPSG:4326"}},"features":[{"type":"Feature","geometry":{"type":"LineString","coordinates":[[-2.08972,4.72778],[-2.08972,4.72778]]}},{"type":"Feature","geometry":{"type":"LineString","coordinates":[[-2.08972,4.72778],[-1.96472,4.72778]]}},{"type":"Feature","geometry":{"type":"LineString","coordinates":[[-2.08972,4.72778],[-1.87,4.72778]]}},{"type":"Feature","geometry":{"type":"LineString","coordinates":[[-2.28722,4.72778],[-1.87,4.72778]]}},{"type":"Feature","geometry":{"type":"LineString","coordinates":[[-2.56528,4.72778],[-1.87,4.72778]]}},{"type":"Feature","geometry":{"type":"LineString","coordinates":[[-2.56528,4.72778],[-1.63639,4.72778]]}},{"type":"Feature","geometry":{"type":"LineString","coordinates":[[-2.56528,4.72778],[-1.62611,4.72778]]}},{"type":"Feature","geometry":{"type":"LineString","coordinates":[[-2.96639,4.72778],[-1.62611,4.72778]]}},{"type":"Feature","geometry":{"type":"LineString","coordinates":[[-3.10555,4.72778],[-1.62611,4.72778]]}},{"type":"Feature","geometry":{"type":"LineString","coordinates":[[-3.10555,4.72778],[-1.62611,4.72778]]}},{"type":"Feature","geometry":{"type":"LineString","coordinates":[[-3.10555,4.72778],[-1.62611,4.72778]]}},{"type":"Feature","geometry":{"type":"LineString","coordinates":[[-3.10555,4.72778],[-1.62611,4.72778]]}},{"type":"Feature","geometry":{"type":"LineString","coordinates":[[-3.10555,4.72778],[-1.62611,4.72778]]}},{"type":"Feature","geometry":{"type":"LineString","coordinates":[[-3.10555,4.72778],[-1.12944,4.72778]]}},{"type":"Feature","geometry":{"type":"LineString","coordinates":[[-3.10555,4.72778],[-0.79972,4.72778]]}},{"type":"Feature","geometry":{"type":"LineString","coordinates":[[-3.10555,4.72778],[-0.79972,4.72778]]}},{"type":"Feature","geometry":{"type":"LineString","coordinates":[[-3.10555,4.72778],[-0.79972,4.72778]]}},{"type":"Feature","geometry":{"type":"LineString","coordinates":[[-3.10555,4.72778],[-0.58778,4.72778]]}},{"type":"Feature","geometry":{"type":"LineString","coordinates":[[-3.10555,4.72778],[-0.58778,4.72778]]}},{"type":"Feature","geometry":{"type":"LineString","coordinates":[[-3.10555,4.72778],[-0.49333,4.72778]]}},{"type":"Feature","geometry":{"type":"LineString","coordinates":[[-3.10555,4.72778],[-0.39722,4.72778]]}},{"type":"Feature","geometry":{"type":"LineString","coordinates":[[-3.10555,4.72778],[-0.39722,4.72778]]}},{"type":"Feature","geometry":{"type":"LineString","coordinates":[[-3.10555,4.72778],[-0.39722,4.72778]]}},{"type":"Feature","geometry":{"type":"LineString","coordinates":[[-3.10555,4.72778],[-0.39722,4.72778]]}},{"type":"Feature","geometry":{"type":"LineString","coordinates":[[-3.10555,4.72778],[-0.39722,4.72778]]}},{"type":"Feature","geometry":{"type":"LineString","coordinates":[[-3.10555,4.72778],[0.06444,4.72778]]}},{"type":"Feature","geometry":{"type":"LineString","coordinates":[[-3.10555,4.72778],[0.06444,4.72778]]}},{"type":"Feature","geometry":{"type":"LineString","coordinates":[[-3.10555,4.72778],[0.06444,4.72778]]}},{"type":"Feature","geometry":{"type":"LineString","coordinates":[[-3.10555,4.72778],[0.68417,4.72778]]}},{"type":"Feature","geometry":{"type":"LineString","coordinates":[[-3.10555,4.72778],[0.92,4.72778]]}},{"type":"Feature","geometry":{"type":"LineString","coordinates":[[-3.10555,4.72778],[0.92,4.72778]]}},{"type":"Feature","geometry":{"type":"LineString","coordinates":[[-3.10555,4.72778],[0.92,4.72778]]}},{"type":"Feature","geometry":{"type":"LineString","coordinates":[[-3.10555,4.72778],[0.98972,4.72778]]}},{"type":"Feature","geometry":{"type":"LineString","coordinates":[[-3.10555,4.72778],[0.98972,4.72778]]}},{"type":"Feature","geometry":{"type":"LineString","coordinates":[[-3.10555,4.72778],[0.98972,4.72778]]}},{"type":"Feature","geometry":{"type":"LineString","coordinates":[[-3.10555,4.72778],[0.98972,4.72778]]}},{"type":"Feature","geometry":{"type":"LineString","coordinates":[[-3.10555,4.72778],[1.06167,4.72778]]}},{"type":"Feature","geometry":{"type":"LineString","coordinates":[[-3.10555,4.72778],[1.06167,4.72778]]}},{"type":"Feature","geometry":{"type":"LineString","coordinates":[[-3.10555,4.72778],[1.06167,4.72778]]}},{"type":"Feature","geometry":{"type":"LineString","coordinates":[[-3.10555,4.72778],[1.06167,4.72778]]}},{"type":"Feature","geometry":{"type":"LineString","coordinates":[[-3.10555,4.72778],[1.06167,4.72778]]}},{"type":"Feature","geometry":{"type":"LineString","coordinates":[[-3.10555,4.72778],[1.06167,4.72778]]}},{"type":"Feature","geometry":{"type":"LineString","coordinates":[[-3.10555,4.72778],[1.06167,4.72778]]}},{"type":"Feature","geometry":{"type":"LineString","coordinates":[[-3.10555,4.72778],[1.06167,4.72778]]}},{"type":"Feature","geometry":{"type":"LineString","coordinates":[[-3.10555,4.72778],[1.20385,4.72778]]}},{"type":"Feature","geometry":{"type":"LineString","coordinates":[[-3.10555,4.72778],[1.20385,4.72778]]}},{"type":"Feature","geometry":{"type":"LineString","coordinates":[[-3.10555,4.72778],[1.20385,4.72778]]}},{"type":"Feature","geometry":{"type":"LineString","coordinates":[[-3.10555,4.72778],[1.20385,4.72778]]}},{"type":"Feature","geometry":{"type":"LineString","coordinates":[[-3.16945,4.72778],[1.20385,4.72778]]}},{"type":"Feature","geometry":{"type":"LineString","coordinates":[[-3.16945,4.72778],[1.20385,4.72778]]}},{"type":"Feature","geometry":{"type":"LineString","coordinates":[[-3.16945,4.72778],[1.20385,4.72778]]}},{"type":"Feature","geometry":{"type":"LineString","coordinates":[[-3.16945,4.72778],[1.20385,4.72778]]}},{"type":"Feature","geometry":{"type":"LineString","coordinates":[[-3.16945,4.72778],[1.20385,4.72778]]}},{"type":"Feature","geometry":{"type":"LineString","coordinates":[[-3.24917,4.72778],[1.20385,4.72778]]}},{"type":"Feature","geometry":{"type":"LineString","coordinates":[[-3.24917,4.72778],[1.20385,4.72778]]}},{"type":"Feature","geometry":{"type":"LineString","coordinates":[[-3.24917,4.72778],[1.20385,4.72778]]}},{"type":"Feature","geometry":{"type":"LineString","coordinates":[[-3.24917,4.72778],[1.20385,4.72778]]}},{"type":"Feature","geometry":{"type":"LineString","coordinates":[[-3.24917,4.72778],[1.20385,4.72778]]}},{"type":"Feature","geometry":{"type":"LineString","coordinates":[[-3.24917,4.72778],[1.20385,4.72778]]}},{"type":"Feature","geometry":{"type":"LineString","coordinates":[[-3.24917,4.72778],[1.20385,4.72778]]}},{"type":"Feature","geometry":{"type":"LineString","coordinates":[[-3.24917,4.72778],[1.20385,4.72778]]}},{"type":"Feature","geometry":{"type":"LineString","coordinates":[[-3.24917,4.72778],[1.20385,4.72778]]}},{"type":"Feature","geometry":{"type":"LineString","coordinates":[[-3.24917,4.72778],[1.20385,4.72778]]}},{"type":"Feature","geometry":{"type":"LineString","coordinates":[[-3.24917,4.72778],[1.20385,4.72778]]}},{"type":"Feature","geometry":{"type":"LineString","coordinates":[[-3.24917,4.72778],[1.20385,4.72778]]}},{"type":"Feature","geometry":{"type":"LineString","coordinates":[[-3.24917,4.72778],[1.20385,4.72778]]}},{"type":"Feature","geometry":{"type":"LineString","coordinates":[[-3.24917,4.72778],[1.20385,4.72778]]}},{"type":"Feature","geometry":{"type":"LineString","coordinates":[[-3.24917,4.72778],[1.20385,4.72778]]}},{"type":"Feature","geometry":{"type":"LineString","coordinates":[[-3.24917,4.72778],[1.20385,4.72778]]}},{"type":"Feature","geometry":{"type":"LineString","coordinates":[[-3.24917,4.72778],[1.20385,4.72778]]}},{"type":"Feature","geometry":{"type":"LineString","coordinates":[[-3.24917,4.72778],[1.20385,4.72778]]}},{"type":"Feature","geometry":{"type":"LineString","coordinates":[[-3.24917,4.72778],[1.20385,4.72778]]}},{"type":"Feature","geometry":{"type":"LineString","coordinates":[[-3.24917,4.72778],[1.20385,4.72778]]}},{"type":"Feature","geometry":{"type":"LineString","coordinates":[[-3.24917,4.72778],[1.20385,4.72778]]}},{"type":"Feature","geometry":{"type":"LineString","coordinates":[[-3.24917,4.72778],[1.20385,4.72778]]}},{"type":"Feature","geometry":{"type":"LineString","coordinates":[[-3.24917,4.72778],[1.20385,4.72778]]}},{"type":"Feature","geometry":{"type":"LineString","coordinates":[[-3.24917,4.72778],[1.20385,4.72778]]}},{"type":"Feature","geometry":{"type":"LineString","coordinates":[[-3.24917,4.72778],[1.20385,4.72778]]}},{"type":"Feature","geometry":{"type":"LineString","coordinates":[[-3.24917,4.72778],[1.20385,4.72778]]}},{"type":"Feature","geometry":{"type":"LineString","coordinates":[[-3.24917,4.72778],[1.20385,4.72778]]}},{"type":"Feature","geometry":{"type":"LineString","coordinates":[[-3.24917,4.72778],[1.20385,4.72778]]}},{"type":"Feature","geometry":{"type":"LineString","coordinates":[[-3.24917,4.72778],[1.20385,4.72778]]}},{"type":"Feature","geometry":{"type":"LineString","coordinates":[[-3.24917,4.72778],[1.20385,4.72778]]}},{"type":"Feature","geometry":{"type":"LineString","coordinates":[[-3.24917,4.72778],[1.20385,4.72778]]}},{"type":"Feature","geometry":{"type":"LineString","coordinates":[[-3.24917,4.72778],[1.20385,4.72778]]}},{"type":"Feature","geometry":{"type":"LineString","coordinates":[[-3.24917,4.72778],[1.20385,4.72778]]}},{"type":"Feature","geometry":{"type":"LineString","coordinates":[[-3.24917,4.72778],[1.20385,4.72778]]}},{"type":"Feature","geometry":{"type":"LineString","coordinates":[[-3.24917,4.72778],[1.20385,4.72778]]}},{"type":"Feature","geometry":{"type":"LineString","coordinates":[[-3.24917,4.72778],[1.20385,4.72778]]}},{"type":"Feature","geometry":{"type":"LineString","coordinates":[[-3.24917,4.72778],[1.20385,4.72778]]}},{"type":"Feature","geometry":{"type":"LineString","coordinates":[[-3.24917,4.72778],[1.20385,4.72778]]}},{"type":"Feature","geometry":{"type":"LineString","coordinates":[[-3.24917,4.72778],[1.20385,4.72778]]}},{"type":"Feature","geometry":{"type":"LineString","coordinates":[[-3.24917,4.72778],[1.20385,4.72778]]}},{"type":"Feature","geometry":{"type":"LineString","coordinates":[[-3.24917,4.72778],[1.20385,4.72778]]}},{"type":"Feature","geometry":{"type":"LineString","coordinates":[[-3.24917,4.72778],[1.20385,4.72778]]}},{"type":"Feature","geometry":{"type":"LineString","coordinates":[[-3.24917,4.72778],[1.20385,4.72778]]}},{"type":"Feature","geometry":{"type":"LineString","coordinates":[[-3.24917,4.72778],[1.20385,4.72778]]}},{"type":"Feature","geometry":{"type":"LineString","coordinates":[[-3.24917,4.72778],[1.20385,4.72778]]}},{"type":"Feature","geometry":{"type":"LineString","coordinates":[[-3.24917,4.72778],[1.20385,4.72778]]}},{"type":"Feature","geometry":{"type":"LineString","coordinates":[[-3.24917,4.72778],[1.20385,4.72778]]}},{"type":"Feature","geometry":{"type":"LineString","coordinates":[[-3.24917,4.72778],[1.20385,4.72778]]}},{"type":"Feature","geometry":{"type":"LineString","coordinates":[[-3.24917,4.72778],[1.20385,4.72778]]}},{"type":"Feature","geometry":{"type":"LineString","coordinates":[[-3.24917,4.72778],[1.20385,4.72778]]}},{"type":"Feature","geometry":{"type":"LineString","coordinates":[[-3.24917,4.72778],[1.20385,4.72778]]}},{"type":"Feature","geometry":{"type":"LineString","coordinates":[[-3.24917,4.72778],[1.20385,4.72778]]}},{"type":"Feature","geometry":{"type":"LineString","coordinates":[[-3.24917,4.72778],[1.20385,4.72778]]}},{"type":"Feature","geometry":{"type":"LineString","coordinates":[[-3.24917,4.72778],[1.20385,4.72778]]}},{"type":"Feature","geometry":{"type":"LineString","coordinates":[[-3.24917,4.72778],[1.20385,4.72778]]}},{"type":"Feature","geometry":{"type":"LineString","coordinates":[[-3.24917,4.72778],[1.20385,4.72778]]}},{"type":"Feature","geometry":{"type":"LineString","coordinates":[[-3.24917,4.72778],[1.20385,4.72778]]}},{"type":"Feature","geometry":{"type":"LineString","coordinates":[[-3.24917,4.72778],[1.20385,4.72778]]}},{"type":"Feature","geometry":{"type":"LineString","coordinates":[[-3.24917,4.72778],[1.20385,4.72778]]}},{"type":"Feature","geometry":{"type":"LineString","coordinates":[[-3.24917,4.72778],[1.20385,4.72778]]}},{"type":"Feature","geometry":{"type":"LineString","coordinates":[[-3.24917,4.72778],[1.20385,4.72778]]}},{"type":"Feature","geometry":{"type":"LineString","coordinates":[[-3.24917,4.72778],[1.20385,4.72778]]}},{"type":"Feature","geometry":{"type":"LineString","coordinates":[[-3.24917,4.72778],[1.20385,4.72778]]}},{"type":"Feature","geometry":{"type":"LineString","coordinates":[[-3.24917,4.72778],[1.20385,4.72778]]}},{"type":"Feature","geometry":{"type":"LineString","coordinates":[[-3.24917,4.72778],[1.20385,4.72778]]}},{"type":"Feature","geometry":{"type":"LineString","coordinates":[[-3.24917,4.72778],[1.20385,4.72778]]}},{"type":"Feature","geometry":{"type":"LineString","coordinates":[[-3.24917,4.72778],[1.20385,4.72778]]}},{"type":"Feature","geometry":{"type":"LineString","coordinates":[[-3.24917,4.72778],[1.20385,4.72778]]}},{"type":"Feature","geometry":{"type":"LineString","coordinates":[[-3.24917,4.72778],[1.20385,4.72778]]}},{"type":"Feature","geometry":{"type":"LineString","coordinates":[[-3.24917,4.72778],[1.20385,4.72778]]}},{"type":"Feature","geometry":{"type":"LineString","coordinates":[[-3.24917,4.72778],[1.20385,4.72778]]}},{"type":"Feature","geometry":{"type":"LineString","coordinates":[[-3.24917,4.72778],[1.20385,4.72778]]}},{"type":"Feature","geometry":{"type":"LineString","coordinates":[[-3.24917,4.72778],[1.20385,4.72778]]}},{"type":"Feature","geometry":{"type":"LineString","coordinates":[[-3.24917,4.72778],[1.20385,4.72778]]}},{"type":"Feature","geometry":{"type":"LineString","coordinates":[[-3.24917,4.72778],[1.20385,4.72778]]}},{"type":"Feature","geometry":{"type":"LineString","coordinates":[[-3.24917,4.72778],[1.20385,4.72778]]}},{"type":"Feature","geometry":{"type":"LineString","coordinates":[[-3.24917,4.72778],[1.20385,4.72778]]}},{"type":"Feature","geometry":{"type":"LineString","coordinates":[[-3.24917,4.72778],[1.20385,4.72778]]}},{"type":"Feature","geometry":{"type":"LineString","coordinates":[[-3.24917,4.72778],[1.20385,4.72778]]}},{"type":"Feature","geometry":{"type":"LineString","coordinates":[[-3.24917,4.72778],[1.20385,4.72778]]}},{"type":"Feature","geometry":{"type":"LineString","coordinates":[[-3.24917,4.72778],[1.20385,4.72778]]}},{"type":"Feature","geometry":{"type":"LineString","coordinates":[[-3.24917,4.72778],[1.20385,4.72778]]}},{"type":"Feature","geometry":{"type":"LineString","coordinates":[[-3.24917,4.72778],[1.20385,4.72778]]}},{"type":"Feature","geometry":{"type":"LineString","coordinates":[[-3.24917,4.72778],[1.20385,4.72778]]}},{"type":"Feature","geometry":{"type":"LineString","coordinates":[[-3.24917,4.72778],[1.20385,4.72778]]}},{"type":"Feature","geometry":{"type":"LineString","coordinates":[[-3.24917,4.72778],[1.20385,4.72778]]}},{"type":"Feature","geometry":{"type":"LineString","coordinates":[[-3.24917,4.72778],[1.20385,4.72778]]}},{"type":"Feature","geometry":{"type":"LineString","coordinates":[[-3.24917,4.72778],[1.20385,4.72778]]}},{"type":"Feature","geometry":{"type":"LineString","coordinates":[[-3.24917,4.72778],[1.20385,4.72778]]}},{"type":"Feature","geometry":{"type":"LineString","coordinates":[[-3.24917,4.72778],[1.20385,4.72778]]}},{"type":"Feature","geometry":{"type":"LineString","coordinates":[[-3.24917,4.72778],[1.20385,4.72778]]}},{"type":"Feature","geometry":{"type":"LineString","coordinates":[[-3.24917,4.72778],[1.20385,4.72778]]}},{"type":"Feature","geometry":{"type":"LineString","coordinates":[[-3.24917,4.72778],[1.20385,4.72778]]}},{"type":"Feature","geometry":{"type":"LineString","coordinates":[[-3.24917,4.72778],[1.20385,4.72778]]}},{"type":"Feature","geometry":{"type":"LineString","coordinates":[[-3.24917,4.72778],[1.20385,4.72778]]}},{"type":"Feature","geometry":{"type":"LineString","coordinates":[[-3.24917,4.72778],[1.20385,4.72778]]}},{"type":"Feature","geometry":{"type":"LineString","coordinates":[[-3.24917,4.72778],[1.20385,4.72778]]}},{"type":"Feature","geometry":{"type":"LineString","coordinates":[[-3.24917,4.72778],[1.20385,4.72778]]}},{"type":"Feature","geometry":{"type":"LineString","coordinates":[[-3.24917,4.72778],[1.20385,4.72778]]}},{"type":"Feature","geometry":{"type":"LineString","coordinates":[[-3.24917,4.72778],[1.20385,4.72778]]}},{"type":"Feature","geometry":{"type":"LineString","coordinates":[[-3.24917,4.72778],[1.20385,4.72778]]}}]}