{"type":"FeatureCollection","crs":{"type":"name","properties":{"name":"EPSG:4326"}},"features":[{"type":"Feature","geometry":{"type":"LineString","coordinates":[[36.83776,32.3136],[36.83776,32.3136]]}},{"type":"Feature","geometry":{"type":"LineString","coordinates":[[36.67471,32.3136],[36.83776,32.3136]]}},{"type":"Feature","geometry":{"type":"LineString","coordinates":[[36.40026,32.3136],[36.83776,32.3136]]}},{"type":"Feature","geometry":{"type":"LineString","coordinates":[[36.32499,32.3136],[36.83776,32.3136]]}},{"type":"Feature","geometry":{"type":"LineString","coordinates":[[36.32499,32.3136],[37.09859,32.3136]]}},{"type":"Feature","geometry":{"type":"LineString","coordinates":[[36.08027,32.3136],[37.09859,32.3136]]}},{"type":"Feature","geometry":{"type":"LineString","coordinates":[[36.08027,32.3136],[37.36749,32.3136]]}},{"type":"Feature","geometry":{"type":"LineString","coordinates":[[35.63345,32.3136],[37.36749,32.3136]]}},{"type":"Feature","geometry":{"type":"LineString","coordinates":[[35.63345,32.3136],[37.36749,32.3136]]}},{"type":"Feature","geometry":{"type":"LineString","coordinates":[[35.59917,32.3136],[37.36749,32.3136]]}},{"type":"Feature","geometry":{"type":"LineString","coordinates":[[35.59917,32.3136],[37.36749,32.3136]]}},{"type":"Feature","geometry":{"type":"LineString","coordinates":[[35.59917,32.3136],[37.36749,32.3136]]}},{"type":"Feature","geometry":{"type":"LineString","coordinates":[[35.59917,32.3136],[37.6361,32.3136]]}},{"type":"Feature","geometry":{"type":"LineString","coordinates":[[35.59917,32.3136],[37.6361,32.3136]]}},{"type":"Feature","geometry":{"type":"LineString","coordinates":[[35.59917,32.3136],[37.6361,32.3136]]}},{"type":"Feature","geometry":{"type":"LineString","coordinates":[[35.59917,32.3136],[37.90637,32.3136]]}},{"type":"Feature","geometry":{"type":"LineString","coordinates":[[35.59917,32.3136],[37.90637,32.3136]]}},{"type":"Feature","geometry":{"type":"LineString","coordinates":[[35.59054,32.3136],[37.90637,32.3136]]}},{"type":"Feature","geometry":{"type":"LineString","coordinates":[[35.59054,32.3136],[37.90637,32.3136]]}},{"type":"Feature","geometry":{"type":"LineString","coordinates":[[35.59054,32.3136],[38.17776,32.3136]]}},{"type":"Feature","geometry":{"type":"LineString","coordinates":[[35.59054,32.3136],[38.44971,32.3136]]}},{"type":"Feature","geometry":{"type":"LineString","coordinates":[[35.59054,32.3136],[38.44971,32.3136]]}},{"type":"Feature","geometry":{"type":"LineString","coordinates":[[35.59054,32.3136],[38.44971,32.3136]]}},{"type":"Feature","geometry":{"type":"LineString","coordinates":[[35.59054,32.3136],[38.72276,32.3136]]}},{"type":"Feature","geometry":{"type":"LineString","coordinates":[[35.59054,32.3136],[38.72276,32.3136]]}},{"type":"Feature","geometry":{"type":"LineString","coordinates":[[35.59054,32.3136],[38.79455,32.3136]]}},{"type":"Feature","geometry":{"type":"LineString","coordinates":[[35.59054,32.3136],[38.79455,32.3136]]}},{"type":"Feature","geometry":{"type":"LineString","coordinates":[[35.59054,32.3136],[38.79455,32.3136]]}},{"type":"Feature","geometry":{"type":"LineString","coordinates":[[35.59054,32.3136],[38.79455,32.3136]]}},{"type":"Feature","geometry":{"type":"LineString","coordinates":[[35.59054,32.3136],[38.79455,32.3136]]}},{"type":"Feature","geometry":{"type":"LineString","coordinates":[[35.59054,32.3136],[38.79455,32.3136]]}},{"type":"Feature","geometry":{"type":"LineString","coordinates":[[35.59054,32.3136],[38.79455,32.3136]]}},{"type":"Feature","geometry":{"type":"LineString","coordinates":[[35.59054,32.3136],[38.79455,32.3136]]}},{"type":"Feature","geometry":{"type":"LineString","coordinates":[[35.59054,32.3136],[38.79455,32.3136]]}},{"type":"Feature","geometry":{"type":"LineString","coordinates":[[35.59054,32.3136],[38.79455,32.3136]]}},{"type":"Feature","geometry":{"type":"LineString","coordinates":[[35.59054,32.3136],[40.27748,32.3136]]}},{"type":"Feature","geometry":{"type":"LineString","coordinates":[[35.59054,32.3136],[40.27748,32.3136]]}},{"type":"Feature","geometry":{"type":"LineString","coordinates":[[35.59054,32.3136],[40.27748,32.3136]]}},{"type":"Feature","geometry":{"type":"LineString","coordinates":[[35.59054,32.3136],[40.27748,32.3136]]}},{"type":"Feature","geometry":{"type":"LineString","coordinates":[[35.59054,32.3136],[40.27748,32.3136]]}},{"type":"Feature","geometry":{"type":"LineString","coordinates":[[35.59054,32.3136],[41.00388,32.3136]]}},{"type":"Feature","geometry":{"type":"LineString","coordinates":[[35.59054,32.3136],[41.00388,32.3136]]}},{"type":"Feature","geometry":{"type":"LineString","coordinates":[[35.59054,32.3136],[41.00388,32.3136]]}},{"type":"Feature","geometry":{"type":"LineString","coordinates":[[35.59054,32.3136],[41.00388,32.3136]]}},{"type":"Feature","geometry":{"type":"LineString","coordinates":[[35.59054,32.3136],[41.00388,32.3136]]}},{"type":"Feature","geometry":{"type":"LineString","coordinates":[[35.59054,32.3136],[41.00388,32.3136]]}},{"type":"Feature","geometry":{"type":"LineString","coordinates":[[35.59054,32.3136],[41.00388,32.3136]]}},{"type":"Feature","geometry":{"type":"LineString","coordinates":[[35.59054,32.3136],[41.00388,32.3136]]}},{"type":"Feature","geometry":{"type":"LineString","coordinates":[[35.59054,32.3136],[41.00388,32.3136]]}},{"type":"Feature","geometry":{"type":"LineString","coordinates":[[35.59054,32.3136],[41.00388,32.3136]]}},{"type":"Feature","geometry":{"type":"LineString","coordinates":[[35.59054,32.3136],[41.00388,32.3136]]}},{"type":"Feature","geometry":{"type":"LineString","coordinates":[[35.59054,32.3136],[41.00388,32.3136]]}},{"type":"Feature","geometry":{"type":"LineString","coordinates":[[35.59054,32.3136],[41.22915,32.3136]]}},{"type":"Feature","geometry":{"type":"LineString","coordinates":[[35.59054,32.3136],[41.22915,32.3136]]}},{"type":"Feature","geometry":{"type":"LineString","coordinates":[[35.59054,32.3136],[41.22915,32.3136]]}},{"type":"Feature","geometry":{"type":"LineString","coordinates":[[35.59054,32.3136],[41.22915,32.3136]]}},{"type":"Feature","geometry":{"type":"LineString","coordinates":[[35.59054,32.3136],[41.22915,32.3136]]}},{"type":"Feature","geometry":{"type":"LineString","coordinates":[[35.59054,32.3136],[41.22915,32.3136]]}},{"type":"Feature","geometry":{"type":"LineString","coordinates":[[35.59054,32.3136],[41.22915,32.3136]]}},{"type":"Feature","geometry":{"type":"LineString","coordinates":[[35.59054,32.3136],[41.27776,32.3136]]}},{"type":"Feature","geometry":{"type":"LineString","coordinates":[[35.59054,32.3136],[41.27776,32.3136]]}},{"type":"Feature","geometry":{"type":"LineString","coordinates":[[35.59054,32.3136],[41.27776,32.3136]]}},{"type":"Feature","geometry":{"type":"LineString","coordinates":[[35.59054,32.3136],[41.38387,32.3136]]}},{"type":"Feature","geometry":{"type":"LineString","coordinates":[[35.59054,32.3136],[41.38387,32.3136]]}},{"type":"Feature","geometry":{"type":"LineString","coordinates":[[35.59054,32.3136],[41.38387,32.3136]]}},{"type":"Feature","geometry":{"type":"LineString","coordinates":[[35.59054,32.3136],[41.38387,32.3136]]}},{"type":"Feature","geometry":{"type":"LineString","coordinates":[[35.59054,32.3136],[41.38387,32.3136]]}},{"type":"Feature","geometry":{"type":"LineString","coordinates":[[35.59054,32.3136],[41.38387,32.3136]]}},{"type":"Feature","geometry":{"type":"LineString","coordinates":[[35.59054,32.3136],[41.38387,32.3136]]}},{"type":"Feature","geometry":{"type":"LineString","coordinates":[[35.59054,32.3136],[41.38387,32.3136]]}},{"type":"Feature","geometry":{"type":"LineString","coordinates":[[35.59054,32.3136],[41.38387,32.3136]]}},{"type":"Feature","geometry":{"type":"LineString","coordinates":[[35.59054,32.3136],[41.38387,32.3136]]}},{"type":"Feature","geometry":{"type":"LineString","coordinates":[[35.59054,32.3136],[41.38387,32.3136]]}},{"type":"Feature","geometry":{"type":"LineString","coordinates":[[35.59054,32.3136],[41.38387,32.3136]]}},{"type":"Feature","geometry":{"type":"LineString","coordinates":[[35.59054,32.3136],[41.38387,32.3136]]}},{"type":"Feature","geometry":{"type":"LineString","coordinates":[[35.59054,32.3136],[41.38387,32.3136]]}},{"type":"Feature","geometry":{"type":"LineString","coordinates":[[35.59054,32.3136],[41.38387,32.3136]]}},{"type":"Feature","geometry":{"type":"LineString","coordinates":[[35.59054,32.3136],[41.38387,32.3136]]}},{"type":"Feature","geometry":{"type":"LineString","coordinates":[[35.59054,32.3136],[41.38387,32.3136]]}},{"type":"Feature","geometry":{"type":"LineString","coordinates":[[35.59054,32.3136],[41.38387,32.3136]]}},{"type":"Feature","geometry":{"type":"LineString","coordinates":[[35.59054,32.3136],[41.38387,32.3136]]}},{"type":"Feature","geometry":{"type":"LineString","coordinates":[[35.59054,32.3136],[41.38387,32.3136]]}},{"type":"Feature","geometry":{"type":"LineString","coordinates":[[35.59054,32.3136],[41.38387,32.3136]]}},{"type":"Feature","geometry":{"type":"LineString","coordinates":[[35.59054,32.3136],[41.38387,32.3136]]}},{"type":"Feature","geometry":{"type":"LineString","coordinates":[[35.59054,32.3136],[41.38387,32.3136]]}},{"type":"Feature","geometry":{"type":"LineString","coordinates":[[35.59054,32.3136],[41.40304,32.3136]]}},{"type":"Feature","geometry":{"type":"LineString","coordinates":[[35.59054,32.3136],[41.83526,32.3136]]}},{"type":"Feature","geometry":{"type":"LineString","coordinates":[[35.59054,32.3136],[41.83526,32.3136]]}},{"type":"Feature","geometry":{"type":"LineString","coordinates":[[35.59054,32.3136],[41.83526,32.3136]]}},{"type":"Feature","geometry":{"type":"LineString","coordinates":[[35.59054,32.3136],[41.83526,32.3136]]}},{"type":"Feature","geometry":{"type":"LineString","coordinates":[[35.59054,32.3136],[41.83526,32.3136]]}},{"type":"Feature","geometry":{"type":"LineString","coordinates":[[35.59054,32.3136],[41.83526,32.3136]]}},{"type":"Feature","geometry":{"type":"LineString","coordinates":[[35.59054,32.3136],[41.83526,32.3136]]}},{"type":"Feature","geometry":{"type":"LineString","coordinates":[[35.59054,32.3136],[41.83526,32.3136]]}},{"type":"Feature","geometry":{"type":"LineString","coordinates":[[35.59054,32.3136],[41.83526,32.3136]]}},{"type":"Feature","geometry":{"type":"LineString","coordinates":[[35.59054,32.3136],[41.83526,32.3136]]}},{"type":"Feature","geometry":{"type":"LineString","coordinates":[[35.59054,32.3136],[41.83526,32.3136]]}},{"type":"Feature","geometry":{"type":"LineString","coordinates":[[35.59054,32.3136],[41.83526,32.3136]]}},{"type":"Feature","geometry":{"type":"LineString","coordinates":[[35.59054,32.3136],[41.83526,32.3136]]}},{"type":"Feature","geometry":{"type":"LineString","coordinates":[[35.59054,32.3136],[41.83526,32.3136]]}},{"type":"Feature","geometry":{"type":"LineString","coordinates":[[35.59054,32.3136],[41.83526,32.3136]]}},{"type":"Feature","geometry":{"type":"LineString","coordinates":[[35.59054,32.3136],[41.83526,32.3136]]}},{"type":"Feature","geometry":{"type":"LineString","coordinates":[[35.59054,32.3136],[41.83526,32.3136]]}},{"type":"Feature","geometry":{"type":"LineString","coordinates":[[35.59054,32.3136],[41.83526,32.3136]]}},{"type":"Feature","geometry":{"type":"LineString","coordinates":[[35.59054,32.3136],[41.83526,32.3136]]}},{"type":"Feature","geometry":{"type":"LineString","coordinates":[[35.59054,32.3136],[42.37385,32.3136]]}},{"type":"Feature","geometry":{"type":"LineString","coordinates":[[35.59054,32.3136],[42.37385,32.3136]]}},{"type":"Feature","geometry":{"type":"LineString","coordinates":[[35.59054,32.3136],[42.37385,32.3136]]}},{"type":"Feature","geometry":{"type":"LineString","coordinates":[[35.59054,32.3136],[42.37385,32.3136]]}},{"type":"Feature","geometry":{"type":"LineString","coordinates":[[35.59054,32.3136],[42.37385,32.3136]]}},{"type":"Feature","geometry":{"type":"LineString","coordinates":[[35.59054,32.3136],[42.37385,32.3136]]}},{"type":"Feature","geometry":{"type":"LineString","coordinates":[[35.59054,32.3136],[42.37385,32.3136]]}},{"type":"Feature","geometry":{"type":"LineString","coordinates":[[35.59054,32.3136],[42.37385,32.3136]]}},{"type":"Feature","geometry":{"type":"LineString","coordinates":[[35.59054,32.3136],[42.37385,32.3136]]}},{"type":"Feature","geometry":{"type":"LineString","coordinates":[[35.59054,32.3136],[42.37385,32.3136]]}},{"type":"Feature","geometry":{"type":"LineString","coordinates":[[35.59054,32.3136],[42.37385,32.3136]]}}]}